setup.py
converter/__init__.py
converter/integer_to_english.py
converter/number_to_word.py
number_converter.egg-info/PKG-INFO
number_converter.egg-info/SOURCES.txt
number_converter.egg-info/dependency_links.txt
number_converter.egg-info/not-zip-safe
number_converter.egg-info/top_level.txt