Metadata-Version: 1.0
Name: number-converter
Version: 0.1
Summary: Convert numbers to words
Home-page: UNKNOWN
Author: Jeffrey Cartagena
Author-email: jose.cartagena@upr.edu
License: MIT
Platform: UNKNOWN
